{
  "gitSyncId": "6791298af5b17f4ec0cc8d73_26ec691c-2ad1-4150-99d9-402520d36a5b",
  "id": "Отчёт_report_approved",
  "pluginId": "postgres-plugin",
  "pluginType": "DB",
  "unpublishedAction": {
    "actionConfiguration": {
      "body": "INSERT INTO appsmith.report_status_history (\n\tsession_id,\n\tcomment,\n\tcreated_date,\n\tdirectory_inn_id,\n\tstatus_id,\n\treport_id\n)\nVALUES (\n\t{{ appsmith.store.user_session.user_session_id }}, -- ID сессии пользователя\n\t'Утверждение отчёта',      -- Комментарий\n\tCURRENT_TIMESTAMP,              -- Текущая дата и время\n\t{{ appsmith.store.user.ou_id }}, -- Значение FK ИНН (directory_inn_id)\n\t5,\t\t-- FK Статус (фиксированное значение)\n\t{{appsmith.store.selected_report.report_id}}\n);",
      "encodeParamsToggle": true,
      "paginationType": "NONE",
      "pluginSpecifiedTemplates": [
        {
          "value": false
        }
      ],
      "timeoutInMillisecond": 10000
    },
    "confirmBeforeExecute": false,
    "datasource": {
      "id": "Appsmith CAD Внутренний",
      "isAutoGenerated": false,
      "name": "Appsmith CAD",
      "pluginId": "postgres-plugin"
    },
    "dynamicBindingPathList": [
      {
        "key": "body"
      }
    ],
    "executeOnLoad": false,
    "name": "report_approved",
    "pageId": "Отчёт",
    "userSetOnLoad": false
  }
}