{
  "animateLoading": false,
  "backgroundColor": "#ffffff",
  "borderColor": "",
  "borderWidth": "1",
  "bottomRow": 124,
  "boxShadow": "NONE",
  "children": [
    {
      "bottomRow": 1430,
      "canExtend": false,
      "containerStyle": "none",
      "detachFromLayout": true,
      "isLoading": false,
      "isVisible": true,
      "leftColumn": 0,
      "minHeight": 121.3125,
      "parentColumnSpace": 1,
      "parentId": "kmzfeovatj",
      "parentRowSpace": 1,
      "props": {
        "canExtend": false,
        "children": [],
        "containerStyle": "none",
        "detachFromLayout": true
      },
      "renderMode": "CANVAS",
      "rightColumn": 242.625,
      "topRow": 0,
      "type": "CANVAS_WIDGET",
      "version": 1,
      "widgetId": "2z8j3rv4zp",
      "widgetName": "Canvas1"
    }
  ],
  "containerStyle": "card",
  "displayName": "Container",
  "dynamicBindingPathList": [],
  "dynamicHeight": "FIXED",
  "dynamicPropertyPathList": [],
  "dynamicTriggerPathList": [],
  "flexVerticalAlignment": "stretch",
  "hideCard": false,
  "iconSVG": "/static/media/icon.b4f5f9eb27fc2bb537b53187836aea6c.svg",
  "isCanvas": true,
  "isDeprecated": false,
  "isLoading": false,
  "isVisible": true,
  "key": "vdgxyqzbwv",
  "leftColumn": 0,
  "maxDynamicHeight": 9000,
  "minDynamicHeight": 10,
  "minWidth": 450,
  "needsErrorInfo": false,
  "onCanvasUI": {
    "disableParentSelection": false,
    "focusBGCSSVar": "--on-canvas-ui-widget-focus",
    "focusColorCSSVar": "--on-canvas-ui-widget-selection",
    "selectionBGCSSVar": "--on-canvas-ui-widget-selection",
    "selectionColorCSSVar": "--on-canvas-ui-widget-focus"
  },
  "parentColumnSpace": 3.791015625,
  "parentId": "jpv1oplu21",
  "parentRowSpace": 10,
  "renderMode": "CANVAS",
  "responsiveBehavior": "fill",
  "rightColumn": 64,
  "searchTags": [
    "div",
    "parent",
    "group"
  ],
  "shouldScrollContents": false,
  "tabId": "",
  "tags": [
    "Layout"
  ],
  "thumbnailSVG": "/static/media/thumbnail.6cb355b93146b5347bbb048a568ed446.svg",
  "topRow": 0,
  "type": "CONTAINER_WIDGET",
  "version": 1,
  "widgetId": "kmzfeovatj",
  "widgetName": "UserMenu"
}